drone_pkg/__init__.py
drone_pkg/hover.py
drone_pkg/hover_and_rect.py
drone_pkg/plutodrone.py
drone_pkg/pose_est.py
drone_pkg/quadControl.py
drone_pkg/task1_keyboard.py
pluto_drone_iitpkd/__init__.py
pluto_drone_iitpkd/hover.py
pluto_drone_iitpkd/hover_and_rect.py
pluto_drone_iitpkd/plutodrone.py
pluto_drone_iitpkd/pose_est.py
pluto_drone_iitpkd/quadControl.py
pluto_drone_iitpkd/task1_keyboard.py
pluto_drone_pkg/__init__.py
pluto_drone_pkg/hover.py
pluto_drone_pkg/hover_and_rect.py
pluto_drone_pkg/plutodrone.py
pluto_drone_pkg/pose_est.py
pluto_drone_pkg/quadControl.py
pluto_drone_pkg/task1_keyboard.py
pluto_drone_pkg-0.0.1.4.dist-info/METADATA
pluto_drone_pkg-0.0.1.4.dist-info/WHEEL
pluto_drone_pkg-0.0.1.4.dist-info/top_level.txt
pluto_drone_pkg-0.0.1.4.dist-info/RECORD
